{"uid":"5946fee8-58be-4cd9-81fb-3870f20761d5","match":43,"team":"2673 Tenacious Technicians","Alliance Color":"B2","Scouter Name":"Shamanth ","Starting Position":"3","Auton Cones Lower":0,"Auton Cubes Lower":0,"Auton Cones Mid":0,"Auton Cubes Mid":0,"Auton Cones Upper":1,"Auton Cubes Upper":0,"Auton Charge Station":"Not Attempted","Auton Notes":"Simply moves forward in auton ","Teleop Cones Lower":1,"Teleop Cubes Lower":1,"Teleop Cones Mid":0,"Teleop Cubes Mid":0,"Teleop Cones Upper":0,"Teleop Cubes Upper":0,"Piece Pickup":"Both","Charge Station":"Failed","Station Side":"N/A","Under Defense":"1 - Cannot score under heavy defense","Other Notes":"Terrible balance when moving, tips over a lot.","Defense Rating":"0 - did not play defense","Defense Notes":"N/a","Robot Rating":"1.5 - not a strong scorer or defender","Auton Points":6,"Teleop Points":4,"Total Points":10}