{"uid":"3f31e4a2-660f-402d-bedb-8894578c014f","match":51,"team":"8427 Robo Ravens","Alliance Color":"B3","Scouter Name":"Devesh R","Starting Position":"3","Auton Cones Lower":0,"Auton Cubes Lower":0,"Auton Cones Mid":0,"Auton Cubes Mid":0,"Auton Cones Upper":0,"Auton Cubes Upper":0,"Auton Charge Station":"Engaged","Auton Notes":"","Teleop Cones Lower":0,"Teleop Cubes Lower":2,"Teleop Cones Mid":0,"Teleop Cubes Mid":0,"Teleop Cones Upper":0,"Teleop Cubes Upper":0,"Piece Pickup":"Floor","Charge Station":"Docked","Station Side":"Middle","Under Defense":"2 - Scoring impacted by defense","Other Notes":"","Defense Rating":"2 - prevented some cargo","Defense Notes":"Maintain cargo","Robot Rating":"2 - contribute to score or elite defense","Auton Points":12,"Teleop Points":10,"Total Points":22}