{"uid":"4daa1de6-45a5-4bf9-ba42-3de0a2d7c82b","match":53,"team":"7145 Robocanes","Alliance Color":"R2","Scouter Name":"Aditi","Starting Position":"1","Auton Cones Lower":0,"Auton Cubes Lower":0,"Auton Cones Mid":0,"Auton Cubes Mid":0,"Auton Cones Upper":0,"Auton Cubes Upper":0,"Auton Charge Station":"Not Attempted","Auton Notes":"","Teleop Cones Lower":0,"Teleop Cubes Lower":0,"Teleop Cones Mid":0,"Teleop Cubes Mid":0,"Teleop Cones Upper":0,"Teleop Cubes Upper":0,"Piece Pickup":"N/A","Charge Station":"Docked","Station Side":"Middle","Under Defense":"0 - Was not under heavy defense","Other Notes":"Tipper over a robot","Defense Rating":"2 - prevented some cargo","Defense Notes":"For one, it tipped a robot\nSecond, it got in the way and spun around it","Robot Rating":"2 - contribute to score or elite defense","Auton Points":0,"Teleop Points":6,"Total Points":6}